pi_hardware_info.py
PiHardwareInfo-0.6.1.dist-info/LICENSE
PiHardwareInfo-0.6.1.dist-info/METADATA
PiHardwareInfo-0.6.1.dist-info/WHEEL
PiHardwareInfo-0.6.1.dist-info/top_level.txt
PiHardwareInfo-0.6.1.dist-info/RECORD
