Metadata-Version: 2.2
Name: PiHardwareInfo
Version: 0.6.1
Summary: Get Raspberry Pi hardware info
Author: Rex Zhang
Author-email: rex.zhang@gmail.com
License: MIT
Project-URL: repository, https://github.com/rexzhang/pi-hardware-info
Keywords: raspberrypi
Classifier: Development Status :: 5 - Production/Stable
Classifier: Operating System :: OS Independent
Classifier: Programming Language :: Python :: 3
Classifier: Topic :: Software Development :: Libraries :: Python Modules
Requires-Python: >=3.9
License-File: LICENSE
